{
  "name": "base",
  "description": "Configures basic server parameters: hostname, timezone, kernel modules.",
  "long_description": "# chef-base\n\n## Description\n\nConfigures basic server parameters: hostname, timezone, kernel modules.\n\n## Requirements\n\n### Supported Platforms\n\nThe following platforms are supported by this cookbook, meaning that the recipes run on these platforms without error:\n\n* Ubuntu\n\n## Recipes\n\n* `base` - Configure all parameters\n* `base::hostname` - Configure node hostname\n* `base::modules` - Configure node modules\n* `base::timezone` - Configure node timezone\n\n## Usage\n\nSet your options in role/node and add recipe to run_list.\n\n## Attributes\n\n```ruby\ndefault[:hostname] = nil\ndefault[:timezone] = 'Etc/UTC'\ndefault[:modules]  = []\n```\n\n## TODO\n\n\n## Contributing\n\n1. Fork it\n2. Create your feature branch (`git checkout -b my-new-feature`)\n3. Commit your changes (`git commit -am 'Added some feature'`)\n4. Push to the branch (`git push origin my-new-feature`)\n5. Create new Pull Request\n\n## Contributors\n\n\n## License\n\n**chef-base**\n\n* Freely distributable and licensed under the [MIT license](http://alno.mit-license.org/).\n* Copyright (c) 2012 Alexey Noskov (alexey.noskov@gmail.com) [![endorse](http://api.coderwall.com/alno/endorsecount.png)](http://coderwall.com/alno)\n",
  "maintainer": "Alexey Noskov",
  "maintainer_email": "alexey.noskov@gmail.com",
  "license": "MIT",
  "platforms": {
    "ubuntu": ">= 0.0.0"
  },
  "dependencies": {
  },
  "recommendations": {
  },
  "suggestions": {
  },
  "conflicting": {
  },
  "providing": {
  },
  "replacing": {
  },
  "attributes": {
  },
  "groupings": {
  },
  "recipes": {
    "base": "Configure all parameters",
    "base::hostname": "Configure node hostname",
    "base::modules": "Configure node modules",
    "base::timezone": "Configure node timezone"
  },
  "version": "0.1.0"
}